[
  {
    "sport": "hurling",
    "grade": "senior",
    "competition": "leinster",
    "stage": "First Round",
    "date": "1963-04-28",
    "team1": "Carlow",
    "team2": "Offaly",
    "t1_g": 5,
    "t1_p": 5,
    "t2_g": 3,
    "t2_p": 7,
    "winner": "Carlow",
    "venue": "O'Moore Park, Portlaoise",
    "attendance": null,
    "referee": "J. Hatton (Wicklow)",
    "notes": "",
    "source_url": "https://en.wikipedia.org/wiki/1963_All-Ireland_Senior_Hurling_Championship"
  },
  {
    "sport": "hurling",
    "grade": "senior",
    "competition": "leinster",
    "stage": "Quarter-Final",
    "date": "1963-05-12",
    "team1": "Carlow",
    "team2": "Westmeath",
    "t1_g": 3,
    "t1_p": 8,
    "t2_g": 2,
    "t2_p": 3,
    "winner": "Carlow",
    "venue": "O'Moore Park, Portlaoise",
    "attendance": null,
    "referee": "T. Coleman (Laois)",
    "notes": "",
    "source_url": "https://en.wikipedia.org/wiki/1963_All-Ireland_Senior_Hurling_Championship"
  },
  {
    "sport": "hurling",
    "grade": "senior",
    "competition": "leinster",
    "stage": "Semi-Final",
    "date": "1963-06-30",
    "team1": "Dublin",
    "team2": "Carlow",
    "t1_g": 3,
    "t1_p": 12,
    "t2_g": 3,
    "t2_p": 5,
    "winner": "Dublin",
    "venue": "Nowlan Park, Kilkenny",
    "attendance": null,
    "referee": "E. Kelly (Laois)",
    "notes": "",
    "source_url": "https://en.wikipedia.org/wiki/1963_All-Ireland_Senior_Hurling_Championship"
  },
  {
    "sport": "hurling",
    "grade": "senior",
    "competition": "leinster",
    "stage": "Semi-Final",
    "date": "1963-07-07",
    "team1": "Kilkenny",
    "team2": "Wexford",
    "t1_g": 4,
    "t1_p": 9,
    "t2_g": 3,
    "t2_p": 8,
    "winner": "Kilkenny",
    "venue": "Croke Park, Dublin",
    "attendance": null,
    "referee": "J. Hatton (Wicklow)",
    "notes": "",
    "source_url": "https://en.wikipedia.org/wiki/1963_All-Ireland_Senior_Hurling_Championship"
  },
  {
    "sport": "hurling",
    "grade": "senior",
    "competition": "leinster",
    "stage": "Final",
    "date": "1963-07-21",
    "team1": "Kilkenny",
    "team2": "Dublin",
    "t1_g": 2,
    "t1_p": 10,
    "t2_g": 0,
    "t2_p": 9,
    "winner": "Kilkenny",
    "venue": "Croke Park, Dublin",
    "attendance": 33438,
    "referee": "T. Coleman (Laois)",
    "notes": "",
    "source_url": "https://en.wikipedia.org/wiki/1963_All-Ireland_Senior_Hurling_Championship"
  },
  {
    "sport": "hurling",
    "grade": "senior",
    "competition": "munster",
    "stage": "Quarter-Final",
    "date": "1963-05-26",
    "team1": "Cork",
    "team2": "Clare",
    "t1_g": 4,
    "t1_p": 15,
    "t2_g": 2,
    "t2_p": 11,
    "winner": "Cork",
    "venue": "Thurles Sportsfield, Thurles",
    "attendance": null,
    "referee": null,
    "notes": "",
    "source_url": "https://en.wikipedia.org/wiki/1963_All-Ireland_Senior_Hurling_Championship"
  },
  {
    "sport": "hurling",
    "grade": "senior",
    "competition": "munster",
    "stage": "Quarter-Final",
    "date": "1963-06-09",
    "team1": "Limerick",
    "team2": "Galway",
    "t1_g": 3,
    "t1_p": 9,
    "t2_g": 2,
    "t2_p": 7,
    "winner": "Limerick",
    "venue": "Cusack Park, Ennis",
    "attendance": 10000,
    "referee": null,
    "notes": "",
    "source_url": "https://en.wikipedia.org/wiki/1963_All-Ireland_Senior_Hurling_Championship"
  },
  {
    "sport": "hurling",
    "grade": "senior",
    "competition": "munster",
    "stage": "Semi-Final",
    "date": "1963-06-30",
    "team1": "Tipperary",
    "team2": "Cork",
    "t1_g": 4,
    "t1_p": 7,
    "t2_g": 1,
    "t2_p": 11,
    "winner": "Tipperary",
    "venue": "Gaelic Grounds, Limerick",
    "attendance": 30000,
    "referee": "S. Power (Waterford)",
    "notes": "",
    "source_url": "https://en.wikipedia.org/wiki/1963_All-Ireland_Senior_Hurling_Championship"
  },
  {
    "sport": "hurling",
    "grade": "senior",
    "competition": "munster",
    "stage": "Semi-Final",
    "date": "1963-07-07",
    "team1": "Waterford",
    "team2": "Limerick",
    "t1_g": 2,
    "t1_p": 15,
    "t2_g": 3,
    "t2_p": 6,
    "winner": "Waterford",
    "venue": "Cork Athletic Grounds, Cork",
    "attendance": 24000,
    "referee": null,
    "notes": "",
    "source_url": "https://en.wikipedia.org/wiki/1963_All-Ireland_Senior_Hurling_Championship"
  },
  {
    "sport": "hurling",
    "grade": "senior",
    "competition": "munster",
    "stage": "Final",
    "date": "1963-07-28",
    "team1": "Waterford",
    "team2": "Tipperary",
    "t1_g": 0,
    "t1_p": 11,
    "t2_g": 0,
    "t2_p": 8,
    "winner": "Waterford",
    "venue": "Gaelic Grounds, Limerick",
    "attendance": 36000,
    "referee": "G. FitzGerald (Limerick)",
    "notes": "",
    "source_url": "https://en.wikipedia.org/wiki/1963_All-Ireland_Senior_Hurling_Championship"
  },
  {
    "sport": "hurling",
    "grade": "senior",
    "competition": "all_ireland",
    "stage": "Final",
    "date": "1963-09-01",
    "team1": "Kilkenny",
    "team2": "Waterford",
    "t1_g": 4,
    "t1_p": 17,
    "t2_g": 6,
    "t2_p": 8,
    "winner": "Kilkenny",
    "venue": "Croke Park, Dublin",
    "attendance": 73123,
    "referee": "J. Hatton (Wicklow)",
    "notes": "",
    "source_url": "https://en.wikipedia.org/wiki/1963_All-Ireland_Senior_Hurling_Championship"
  }
]
