[
  {
    "sport": "hurling",
    "grade": "senior",
    "competition": "leinster",
    "stage": "First Round",
    "date": "1964-05-10",
    "team1": "Offaly",
    "team2": "Westmeath",
    "t1_g": 3,
    "t1_p": 7,
    "t2_g": 2,
    "t2_p": 16,
    "winner": "Westmeath",
    "venue": "St Brendan's Park, Birr",
    "attendance": null,
    "referee": null,
    "notes": "",
    "source_url": "https://en.wikipedia.org/wiki/1964_All-Ireland_Senior_Hurling_Championship"
  },
  {
    "sport": "hurling",
    "grade": "senior",
    "competition": "leinster",
    "stage": "First Round",
    "date": "1964-05-10",
    "team1": "Carlow",
    "team2": "Laois",
    "t1_g": 4,
    "t1_p": 12,
    "t2_g": 2,
    "t2_p": 9,
    "winner": "Carlow",
    "venue": "Nowlan Park, Kilkenny",
    "attendance": null,
    "referee": null,
    "notes": "",
    "source_url": "https://en.wikipedia.org/wiki/1964_All-Ireland_Senior_Hurling_Championship"
  },
  {
    "sport": "hurling",
    "grade": "senior",
    "competition": "leinster",
    "stage": "Second Round",
    "date": "1964-06-07",
    "team1": "Carlow",
    "team2": "Westmeath",
    "t1_g": 2,
    "t1_p": 9,
    "t2_g": 1,
    "t2_p": 9,
    "winner": "Carlow",
    "venue": "O'Moore Park, Portlaoise",
    "attendance": null,
    "referee": "E. Kelly",
    "notes": "",
    "source_url": "https://en.wikipedia.org/wiki/1964_All-Ireland_Senior_Hurling_Championship"
  },
  {
    "sport": "hurling",
    "grade": "senior",
    "competition": "leinster",
    "stage": "Semi-Final",
    "date": "1964-06-28",
    "team1": "Dublin",
    "team2": "Carlow",
    "t1_g": 6,
    "t1_p": 11,
    "t2_g": 2,
    "t2_p": 3,
    "winner": "Dublin",
    "venue": "Wexford Park, Wexford",
    "attendance": null,
    "referee": null,
    "notes": "",
    "source_url": "https://en.wikipedia.org/wiki/1964_All-Ireland_Senior_Hurling_Championship"
  },
  {
    "sport": "hurling",
    "grade": "senior",
    "competition": "leinster",
    "stage": "Semi-Final",
    "date": "1964-07-05",
    "team1": "Kilkenny",
    "team2": "Wexford",
    "t1_g": 5,
    "t1_p": 9,
    "t2_g": 4,
    "t2_p": 8,
    "winner": "Kilkenny",
    "venue": "Croke Park, Dublin",
    "attendance": 25700,
    "referee": null,
    "notes": "",
    "source_url": "https://en.wikipedia.org/wiki/1964_All-Ireland_Senior_Hurling_Championship"
  },
  {
    "sport": "hurling",
    "grade": "senior",
    "competition": "leinster",
    "stage": "Final",
    "date": "1964-07-19",
    "team1": "Kilkenny",
    "team2": "Dublin",
    "t1_g": 4,
    "t1_p": 11,
    "t2_g": 1,
    "t2_p": 8,
    "winner": "Kilkenny",
    "venue": "Croke Park, Dublin",
    "attendance": 30103,
    "referee": "J. Dowling (Offaly)",
    "notes": "",
    "source_url": "https://en.wikipedia.org/wiki/1964_All-Ireland_Senior_Hurling_Championship"
  },
  {
    "sport": "hurling",
    "grade": "senior",
    "competition": "munster",
    "stage": "Quarter-Final",
    "date": "1964-05-24",
    "team1": "Clare",
    "team2": "Limerick",
    "t1_g": 4,
    "t1_p": 14,
    "t2_g": 2,
    "t2_p": 6,
    "winner": "Clare",
    "venue": "McDonagh Park, Nenagh",
    "attendance": null,
    "referee": "D. Nealon (Tipperary)",
    "notes": "",
    "source_url": "https://en.wikipedia.org/wiki/1964_All-Ireland_Senior_Hurling_Championship"
  },
  {
    "sport": "hurling",
    "grade": "senior",
    "competition": "munster",
    "stage": "Quarter-Final",
    "date": "1964-06-07",
    "team1": "Cork",
    "team2": "Galway",
    "t1_g": 4,
    "t1_p": 14,
    "t2_g": 2,
    "t2_p": 7,
    "winner": "Cork",
    "venue": "Gaelic Grounds, Limerick",
    "attendance": null,
    "referee": "J. Smyth (Clare)",
    "notes": "",
    "source_url": "https://en.wikipedia.org/wiki/1964_All-Ireland_Senior_Hurling_Championship"
  },
  {
    "sport": "hurling",
    "grade": "senior",
    "competition": "munster",
    "stage": "Semi-Final",
    "date": "1964-06-28",
    "team1": "Cork",
    "team2": "Waterford",
    "t1_g": 4,
    "t1_p": 10,
    "t2_g": 5,
    "t2_p": 6,
    "winner": "Cork",
    "venue": "Thurles Sportsfield, Thurles",
    "attendance": 25000,
    "referee": "G. FitzGerald (Limerick)",
    "notes": "",
    "source_url": "https://en.wikipedia.org/wiki/1964_All-Ireland_Senior_Hurling_Championship"
  },
  {
    "sport": "hurling",
    "grade": "senior",
    "competition": "munster",
    "stage": "Semi-Final",
    "date": "1964-07-05",
    "team1": "Tipperary",
    "team2": "Clare",
    "t1_g": 6,
    "t1_p": 13,
    "t2_g": 2,
    "t2_p": 5,
    "winner": "Tipperary",
    "venue": "Gaelic Grounds, Limerick",
    "attendance": 23000,
    "referee": null,
    "notes": "",
    "source_url": "https://en.wikipedia.org/wiki/1964_All-Ireland_Senior_Hurling_Championship"
  },
  {
    "sport": "hurling",
    "grade": "senior",
    "competition": "munster",
    "stage": "Final",
    "date": "1964-07-26",
    "team1": "Tipperary",
    "team2": "Cork",
    "t1_g": 3,
    "t1_p": 13,
    "t2_g": 1,
    "t2_p": 5,
    "winner": "Tipperary",
    "venue": "Gaelic Grounds, Limerick",
    "attendance": 44245,
    "referee": "J. Smyth (Clare)",
    "notes": "",
    "source_url": "https://en.wikipedia.org/wiki/1964_All-Ireland_Senior_Hurling_Championship"
  },
  {
    "sport": "hurling",
    "grade": "senior",
    "competition": "all_ireland",
    "stage": "Final",
    "date": "1964-09-06",
    "team1": "Tipperary",
    "team2": "Kilkenny",
    "t1_g": 5,
    "t1_p": 13,
    "t2_g": 2,
    "t2_p": 8,
    "winner": "Tipperary",
    "venue": "Croke Park, Dublin",
    "attendance": 71282,
    "referee": "A. Higgins (Galway)",
    "notes": "",
    "source_url": "https://en.wikipedia.org/wiki/1964_All-Ireland_Senior_Hurling_Championship"
  }
]
