[
  {
    "sport": "hurling",
    "grade": "senior",
    "competition": "leinster",
    "stage": "semi-final",
    "date": "1979-06-24",
    "team1": "Kilkenny",
    "team2": "Dublin",
    "t1_g": 4,
    "t1_p": 15,
    "t2_g": 4,
    "t2_p": 11,
    "winner": "Kilkenny",
    "venue": "Geraldine Park",
    "attendance": null,
    "referee": "G Kirwan (Offaly)",
    "notes": "",
    "source_url": "https://en.wikipedia.org/wiki/1979_All-Ireland_Senior_Hurling_Championship"
  },
  {
    "sport": "hurling",
    "grade": "senior",
    "competition": "leinster",
    "stage": "semi-final",
    "date": "1979-06-24",
    "team1": "Wexford",
    "team2": "Offaly",
    "t1_g": 0,
    "t1_p": 17,
    "t2_g": 2,
    "t2_p": 10,
    "winner": "Wexford",
    "venue": "Geraldine Park",
    "attendance": null,
    "referee": "N O'Donoghue (Dublin)",
    "notes": "",
    "source_url": "https://en.wikipedia.org/wiki/1979_All-Ireland_Senior_Hurling_Championship"
  },
  {
    "sport": "hurling",
    "grade": "senior",
    "competition": "leinster",
    "stage": "final",
    "date": "1979-07-15",
    "team1": "Kilkenny",
    "team2": "Wexford",
    "t1_g": 2,
    "t1_p": 21,
    "t2_g": 2,
    "t2_p": 17,
    "winner": "Kilkenny",
    "venue": "Croke Park",
    "attendance": 24991,
    "referee": "G Kirwan (Offaly)",
    "notes": "",
    "source_url": "https://en.wikipedia.org/wiki/1979_All-Ireland_Senior_Hurling_Championship"
  },
  {
    "sport": "hurling",
    "grade": "senior",
    "competition": "munster",
    "stage": "quarter-final",
    "date": "1979-05-27",
    "team1": "Limerick",
    "team2": "Waterford",
    "t1_g": 5,
    "t1_p": 11,
    "t2_g": 2,
    "t2_p": 11,
    "winner": "Limerick",
    "venue": "Páirc Uí Chaoimh",
    "attendance": null,
    "referee": "F Murphy (Cork)",
    "notes": "",
    "source_url": "https://en.wikipedia.org/wiki/1979_All-Ireland_Senior_Hurling_Championship"
  },
  {
    "sport": "hurling",
    "grade": "senior",
    "competition": "munster",
    "stage": "semi-final",
    "date": "1979-06-03",
    "team1": "Cork",
    "team2": "Tipperary",
    "t1_g": 1,
    "t1_p": 14,
    "t2_g": 2,
    "t2_p": 10,
    "winner": "Cork",
    "venue": "Páirc Uí Chaoimh",
    "attendance": 40690,
    "referee": "N Dalton (Waterford)",
    "notes": "",
    "source_url": "https://en.wikipedia.org/wiki/1979_All-Ireland_Senior_Hurling_Championship"
  },
  {
    "sport": "hurling",
    "grade": "senior",
    "competition": "munster",
    "stage": "semi-final",
    "date": "1979-06-10",
    "team1": "Limerick",
    "team2": "Clare",
    "t1_g": 3,
    "t1_p": 19,
    "t2_g": 4,
    "t2_p": 12,
    "winner": "Limerick",
    "venue": "Semple Stadium",
    "attendance": 20791,
    "referee": "F Murphy",
    "notes": "",
    "source_url": "https://en.wikipedia.org/wiki/1979_All-Ireland_Senior_Hurling_Championship"
  },
  {
    "sport": "hurling",
    "grade": "senior",
    "competition": "munster",
    "stage": "final",
    "date": "1979-07-08",
    "team1": "Cork",
    "team2": "Limerick",
    "t1_g": 2,
    "t1_p": 14,
    "t2_g": 0,
    "t2_p": 9,
    "winner": "Cork",
    "venue": "Semple Stadium",
    "attendance": 47849,
    "referee": "G Ryan (Tipperary)",
    "notes": "",
    "source_url": "https://en.wikipedia.org/wiki/1979_All-Ireland_Senior_Hurling_Championship"
  },
  {
    "sport": "hurling",
    "grade": "senior",
    "competition": "all_ireland",
    "stage": "quarter-final",
    "date": "1979-07-01",
    "team1": "Galway",
    "team2": "Laois",
    "t1_g": 1,
    "t1_p": 23,
    "t2_g": 3,
    "t2_p": 10,
    "winner": "Galway",
    "venue": "St. Brendan's Park",
    "attendance": null,
    "referee": "N O'Donoghue (Dublin)",
    "notes": "",
    "source_url": "https://en.wikipedia.org/wiki/1979_All-Ireland_Senior_Hurling_Championship"
  },
  {
    "sport": "hurling",
    "grade": "senior",
    "competition": "all_ireland",
    "stage": "semi-final",
    "date": "1979-08-05",
    "team1": "Galway",
    "team2": "Cork",
    "t1_g": 2,
    "t1_p": 14,
    "t2_g": 1,
    "t2_p": 13,
    "winner": "Galway",
    "venue": "Croke Park",
    "attendance": 12315,
    "referee": "J Rankins (Laois)",
    "notes": "",
    "source_url": "https://en.wikipedia.org/wiki/1979_All-Ireland_Senior_Hurling_Championship"
  },
  {
    "sport": "hurling",
    "grade": "senior",
    "competition": "all_ireland",
    "stage": "final",
    "date": "1979-09-02",
    "team1": "Kilkenny",
    "team2": "Galway",
    "t1_g": 2,
    "t1_p": 12,
    "t2_g": 1,
    "t2_p": 8,
    "winner": "Kilkenny",
    "venue": "Croke Park",
    "attendance": 53535,
    "referee": "G Ryan (Tipperary)",
    "notes": "",
    "source_url": "https://en.wikipedia.org/wiki/1979_All-Ireland_Senior_Hurling_Championship"
  }
]
