[
  {
    "sport": "hurling",
    "grade": "senior",
    "competition": "leinster",
    "stage": "Provincial quarter-final",
    "date": "1996-06-02",
    "team1": "Offaly",
    "team2": "Meath",
    "t1_g": 2,
    "t1_p": 18,
    "t2_g": 2,
    "t2_p": 12,
    "winner": "Offaly",
    "venue": "Croke Park, Dublin",
    "attendance": null,
    "referee": "P. Delaney (Laois)",
    "notes": "",
    "source_url": "https://en.wikipedia.org/wiki/1996_All-Ireland_Senior_Hurling_Championship"
  },
  {
    "sport": "hurling",
    "grade": "senior",
    "competition": "leinster",
    "stage": "Provincial quarter-final",
    "date": "1996-06-02",
    "team1": "Wexford",
    "team2": "Kilkenny",
    "t1_g": 1,
    "t1_p": 14,
    "t2_g": 0,
    "t2_p": 14,
    "winner": "Wexford",
    "venue": "Croke Park, Dublin",
    "attendance": null,
    "referee": "A. Mac Suibhne (Dublin)",
    "notes": "",
    "source_url": "https://en.wikipedia.org/wiki/1996_All-Ireland_Senior_Hurling_Championship"
  },
  {
    "sport": "hurling",
    "grade": "senior",
    "competition": "leinster",
    "stage": "Provincial semi-final",
    "date": "1996-06-23",
    "team1": "Dublin",
    "team2": "Wexford",
    "t1_g": 1,
    "t1_p": 9,
    "t2_g": 2,
    "t2_p": 12,
    "winner": "Wexford",
    "venue": "Croke Park, Dublin",
    "attendance": 30008,
    "referee": "P. Horan (Offaly)",
    "notes": "",
    "source_url": "https://en.wikipedia.org/wiki/1996_All-Ireland_Senior_Hurling_Championship"
  },
  {
    "sport": "hurling",
    "grade": "senior",
    "competition": "leinster",
    "stage": "Provincial semi-final",
    "date": "1996-06-23",
    "team1": "Offaly",
    "team2": "Laois",
    "t1_g": 4,
    "t1_p": 17,
    "t2_g": 2,
    "t2_p": 10,
    "winner": "Offaly",
    "venue": "Croke Park, Dublin",
    "attendance": 30008,
    "referee": "P. Aherne (Carlow)",
    "notes": "",
    "source_url": "https://en.wikipedia.org/wiki/1996_All-Ireland_Senior_Hurling_Championship"
  },
  {
    "sport": "hurling",
    "grade": "senior",
    "competition": "leinster",
    "stage": "Provincial final",
    "date": "1996-07-14",
    "team1": "Wexford",
    "team2": "Offaly",
    "t1_g": 2,
    "t1_p": 23,
    "t2_g": 2,
    "t2_p": 15,
    "winner": "Wexford",
    "venue": "Croke Park, Dublin",
    "attendance": 34365,
    "referee": null,
    "notes": "",
    "source_url": "https://en.wikipedia.org/wiki/1996_All-Ireland_Senior_Hurling_Championship"
  },
  {
    "sport": "hurling",
    "grade": "senior",
    "competition": "munster",
    "stage": "Provincial quarter-final",
    "date": "1996-05-26",
    "team1": "Cork",
    "team2": "Limerick",
    "t1_g": 1,
    "t1_p": 8,
    "t2_g": 3,
    "t2_p": 18,
    "winner": "Limerick",
    "venue": "Páirc Uí Chaoimh, Cork",
    "attendance": null,
    "referee": "W. Barrett (Tipperary)",
    "notes": "",
    "source_url": "https://en.wikipedia.org/wiki/1996_All-Ireland_Senior_Hurling_Championship"
  },
  {
    "sport": "hurling",
    "grade": "senior",
    "competition": "munster",
    "stage": "Provincial quarter-final",
    "date": "1996-06-02",
    "team1": "Waterford",
    "team2": "Tipperary",
    "t1_g": 1,
    "t1_p": 11,
    "t2_g": 1,
    "t2_p": 14,
    "winner": "Tipperary",
    "venue": "Walsh Park, Waterford",
    "attendance": 15655,
    "referee": "D. Murphy (Wexford)",
    "notes": "",
    "source_url": "https://en.wikipedia.org/wiki/1996_All-Ireland_Senior_Hurling_Championship"
  },
  {
    "sport": "hurling",
    "grade": "senior",
    "competition": "munster",
    "stage": "Provincial semi-final",
    "date": "1996-06-15",
    "team1": "Kerry",
    "team2": "Tipperary",
    "t1_g": 2,
    "t1_p": 11,
    "t2_g": 4,
    "t2_p": 19,
    "winner": "Tipperary",
    "venue": "Austin Stack Park, Tralee",
    "attendance": 4300,
    "referee": "J. O'Leary (Cork)",
    "notes": "",
    "source_url": "https://en.wikipedia.org/wiki/1996_All-Ireland_Senior_Hurling_Championship"
  },
  {
    "sport": "hurling",
    "grade": "senior",
    "competition": "munster",
    "stage": "Provincial semi-final",
    "date": "1996-06-16",
    "team1": "Limerick",
    "team2": "Clare",
    "t1_g": 1,
    "t1_p": 13,
    "t2_g": 0,
    "t2_p": 15,
    "winner": "Limerick",
    "venue": "Gaelic Grounds, Limerick",
    "attendance": 43534,
    "referee": "W. Barrett (Tipperary)",
    "notes": "",
    "source_url": "https://en.wikipedia.org/wiki/1996_All-Ireland_Senior_Hurling_Championship"
  },
  {
    "sport": "hurling",
    "grade": "senior",
    "competition": "munster",
    "stage": "Provincial final",
    "date": "1996-07-07",
    "team1": "Limerick",
    "team2": "Tipperary",
    "t1_g": 0,
    "t1_p": 19,
    "t2_g": 1,
    "t2_p": 16,
    "winner": "draw",
    "venue": "Gaelic Grounds, Limerick",
    "attendance": 43525,
    "referee": "J. O'Leary (Cork)",
    "notes": "Drawn match",
    "source_url": "https://en.wikipedia.org/wiki/1996_All-Ireland_Senior_Hurling_Championship"
  },
  {
    "sport": "hurling",
    "grade": "senior",
    "competition": "munster",
    "stage": "Provincial final",
    "date": "1996-07-14",
    "team1": "Limerick",
    "team2": "Tipperary",
    "t1_g": 4,
    "t1_p": 7,
    "t2_g": 0,
    "t2_p": 16,
    "winner": "Limerick",
    "venue": "Páirc Uí Chaoimh, Cork",
    "attendance": 40000,
    "referee": "J. O'Leary (Cork)",
    "notes": "Replay",
    "source_url": "https://en.wikipedia.org/wiki/1996_All-Ireland_Senior_Hurling_Championship"
  },
  {
    "sport": "hurling",
    "grade": "senior",
    "competition": "all_ireland",
    "stage": "Quarter-final",
    "date": "1996-07-20",
    "team1": "Galway",
    "team2": "New York",
    "t1_g": 4,
    "t1_p": 22,
    "t2_g": 0,
    "t2_p": 8,
    "winner": "Galway",
    "venue": "Kenny Park, Athenry",
    "attendance": null,
    "referee": null,
    "notes": "",
    "source_url": "https://en.wikipedia.org/wiki/1996_All-Ireland_Senior_Hurling_Championship"
  },
  {
    "sport": "hurling",
    "grade": "senior",
    "competition": "all_ireland",
    "stage": "Semi-final",
    "date": "1996-08-04",
    "team1": "Limerick",
    "team2": "Antrim",
    "t1_g": 1,
    "t1_p": 17,
    "t2_g": 0,
    "t2_p": 13,
    "winner": "Limerick",
    "venue": "Croke Park, Dublin",
    "attendance": 61937,
    "referee": "P. Aherne (Carlow)",
    "notes": "",
    "source_url": "https://en.wikipedia.org/wiki/1996_All-Ireland_Senior_Hurling_Championship"
  },
  {
    "sport": "hurling",
    "grade": "senior",
    "competition": "all_ireland",
    "stage": "Semi-final",
    "date": "1996-08-04",
    "team1": "Wexford",
    "team2": "Galway",
    "t1_g": 2,
    "t1_p": 13,
    "t2_g": 3,
    "t2_p": 7,
    "winner": "Wexford",
    "venue": "Croke Park, Dublin",
    "attendance": 61937,
    "referee": "J. O'Leary (Cork)",
    "notes": "",
    "source_url": "https://en.wikipedia.org/wiki/1996_All-Ireland_Senior_Hurling_Championship"
  },
  {
    "sport": "hurling",
    "grade": "senior",
    "competition": "all_ireland",
    "stage": "Final",
    "date": "1996-09-01",
    "team1": "Wexford",
    "team2": "Limerick",
    "t1_g": 1,
    "t1_p": 13,
    "t2_g": 0,
    "t2_p": 14,
    "winner": "Wexford",
    "venue": "Croke Park, Dublin",
    "attendance": 65847,
    "referee": "P. Horan (Offaly)",
    "notes": "",
    "source_url": "https://en.wikipedia.org/wiki/1996_All-Ireland_Senior_Hurling_Championship"
  }
]
